[
  {
    "firstName": "Pierre",
    "lastName": "Reichert",
    "gender": "Omnigender",
    "email": "Jamarcus.Beahan81@hotmail.com",
    "jobTitle": "Chief Implementation Planner",
    "street": "Annamarie Junction",
    "city": "Johnstonstead",
    "latitude": -77.2974,
    "longitude": 17.5633,
    "favouriteColour": "#3feb9a",
    "profileImage": "https://www.gravatar.com/avatar/Jamarcus.Beahan81@hotmail.com?s=120&d=identicon",
    "id": 1
  },
  {
    "firstName": "Kirsten",
    "lastName": "Crist",
    "gender": "Transexual female",
    "email": "Susana_Walker@hotmail.com",
    "jobTitle": "Investor Configuration Associate",
    "street": "Ernestine Loaf",
    "city": "West Damionview",
    "latitude": 5.1837,
    "longitude": 33.3007,
    "favouriteColour": "#9ccbbd",
    "profileImage": "https://www.gravatar.com/avatar/Susana_Walker@hotmail.com?s=120&d=identicon",
    "id": 2
  },
  {
    "firstName": "Jade",
    "lastName": "Renner",
    "gender": "Transexual woman",
    "email": "Clement.Leannon@hotmail.com",
    "jobTitle": "Product Optimization Manager",
    "street": "Treutel Cape",
    "city": "Lake Sheridanfield",
    "latitude": -18.2479,
    "longitude": -5.4588,
    "favouriteColour": "#b2a23a",
    "profileImage": "https://www.gravatar.com/avatar/Clement.Leannon@hotmail.com?s=120&d=identicon",
    "id": 3
  },
  {
    "firstName": "Brice",
    "lastName": "Hahn",
    "gender": "Cis male",
    "email": "Gustave_MacGyver@hotmail.com",
    "jobTitle": "International Usability Officer",
    "street": "Denis Bypass",
    "city": "Bossier City",
    "latitude": -43.6278,
    "longitude": -88.4951,
    "favouriteColour": "#5baa2e",
    "profileImage": "https://www.gravatar.com/avatar/Gustave_MacGyver@hotmail.com?s=120&d=identicon",
    "id": 4
  },
  {
    "firstName": "Bettye",
    "lastName": "Simonis",
    "gender": "Cis male",
    "email": "Jonatan49@yahoo.com",
    "jobTitle": "Direct Response Coordinator",
    "street": "E Cedar Street",
    "city": "Kurtshire",
    "latitude": -4.5889,
    "longitude": 103.3593,
    "favouriteColour": "#d8d95b",
    "profileImage": "https://www.gravatar.com/avatar/Jonatan49@yahoo.com?s=120&d=identicon",
    "id": 5
  },
  {
    "firstName": "Patrick",
    "lastName": "Tillman",
    "gender": "Agender",
    "email": "Hertha93@gmail.com",
    "jobTitle": "Chief Program Administrator",
    "street": "Bradley Points",
    "city": "North Lenora",
    "latitude": -61.4926,
    "longitude": 114.3885,
    "favouriteColour": "#eb510b",
    "profileImage": "https://www.gravatar.com/avatar/Hertha93@gmail.com?s=120&d=identicon",
    "id": 6
  },
  {
    "firstName": "Sarina",
    "lastName": "O'Keefe",
    "gender": "Cisgender man",
    "email": "Finn.Legros@yahoo.com",
    "jobTitle": "Global Data Planner",
    "street": "The Poplars",
    "city": "Laurineport",
    "latitude": -35.4791,
    "longitude": 45.3075,
    "favouriteColour": "#204e71",
    "profileImage": "https://www.gravatar.com/avatar/Finn.Legros@yahoo.com?s=120&d=identicon",
    "id": 7
  },
  {
    "firstName": "Verona",
    "lastName": "Keebler",
    "gender": "Gender neutral",
    "email": "Elna_Kuvalis@hotmail.com",
    "jobTitle": "Human Factors Coordinator",
    "street": "N Monroe Street",
    "city": "Melyssaberg",
    "latitude": -63.102,
    "longitude": -26.0081,
    "favouriteColour": "#5fd8e4",
    "profileImage": "https://www.gravatar.com/avatar/Elna_Kuvalis@hotmail.com?s=120&d=identicon",
    "id": 8
  },
  {
    "firstName": "Fredrick",
    "lastName": "Cummerata",
    "gender": "Cis female",
    "email": "Maci0@yahoo.com",
    "jobTitle": "Investor Marketing Analyst",
    "street": "Rice Bypass",
    "city": "North Rebaberg",
    "latitude": -84.4847,
    "longitude": 157.8773,
    "favouriteColour": "#2baecd",
    "profileImage": "https://www.gravatar.com/avatar/Maci0@yahoo.com?s=120&d=identicon",
    "id": 9
  },
  {
    "firstName": "Martina",
    "lastName": "Kovacek",
    "gender": "Neither",
    "email": "Marge.Dach0@gmail.com",
    "jobTitle": "Corporate Accountability Planner",
    "street": "Cruickshank Rest",
    "city": "Cormierboro",
    "latitude": 6.4171,
    "longitude": 134.983,
    "favouriteColour": "#9c2838",
    "profileImage": "https://www.gravatar.com/avatar/Marge.Dach0@gmail.com?s=120&d=identicon",
    "id": 10
  },
  {
    "firstName": "Dario",
    "lastName": "Abernathy",
    "gender": "Transexual person",
    "email": "Valentin91@yahoo.com",
    "jobTitle": "Direct Research Associate",
    "street": "Kuvalis Point",
    "city": "Port Nona",
    "latitude": -71.8066,
    "longitude": -95.7907,
    "favouriteColour": "#aa3a90",
    "profileImage": "https://www.gravatar.com/avatar/Valentin91@yahoo.com?s=120&d=identicon",
    "id": 11
  },
  {
    "firstName": "Valentina",
    "lastName": "Funk",
    "gender": "Transexual",
    "email": "Santa5@yahoo.com",
    "jobTitle": "Forward Usability Supervisor",
    "street": "Katherine Shoal",
    "city": "Sunnyvale",
    "latitude": 10.089,
    "longitude": -123.4999,
    "favouriteColour": "#2b91fb",
    "profileImage": "https://www.gravatar.com/avatar/Santa5@yahoo.com?s=120&d=identicon",
    "id": 12
  },
  {
    "firstName": "Savanah",
    "lastName": "Kuhlman",
    "gender": "Cis male",
    "email": "Fay.Collins@gmail.com",
    "jobTitle": "Product Operations Technician",
    "street": "Poplar Road",
    "city": "West Dagmarfort",
    "latitude": -80.9639,
    "longitude": -151.7595,
    "favouriteColour": "#ba4d8a",
    "profileImage": "https://www.gravatar.com/avatar/Fay.Collins@gmail.com?s=120&d=identicon",
    "id": 13
  },
  {
    "firstName": "Era",
    "lastName": "Raynor",
    "gender": "Cisgender male",
    "email": "Hermann.Crona93@yahoo.com",
    "jobTitle": "Corporate Metrics Architect",
    "street": "Kovacek Extension",
    "city": "Mittieworth",
    "latitude": -61.8504,
    "longitude": 93.6373,
    "favouriteColour": "#af5db5",
    "profileImage": "https://www.gravatar.com/avatar/Hermann.Crona93@yahoo.com?s=120&d=identicon",
    "id": 14
  },
  {
    "firstName": "Jillian",
    "lastName": "Mante",
    "gender": "Genderflux",
    "email": "Loyal.Jaskolski@gmail.com",
    "jobTitle": "Dynamic Marketing Director",
    "street": "S 4th Street",
    "city": "Lebsackbury",
    "latitude": 4.5974,
    "longitude": -119.9587,
    "favouriteColour": "#b5713e",
    "profileImage": "https://www.gravatar.com/avatar/Loyal.Jaskolski@gmail.com?s=120&d=identicon",
    "id": 15
  }
]
